LICENSE
MANIFEST.in
README.rst
setup.py
sqlalchemy_repr.py
sqlalchemy_repr.egg-info/PKG-INFO
sqlalchemy_repr.egg-info/SOURCES.txt
sqlalchemy_repr.egg-info/dependency_links.txt
sqlalchemy_repr.egg-info/requires.txt
sqlalchemy_repr.egg-info/top_level.txt
tests/__init__.py
tests/test_readme.py
tests/test_sqlalchemy_repr.py