Metadata-Version: 1.1
Name: sqlalchemy-repr
Version: 0.0.1
Summary: Automatically generates pretty repr of a SQLAlchemy model.
Home-page: https://github.com/manicmaniac/sqlalchemy-repr
Author: Ryosuke Ito
Author-email: rito.0305@gmail.com
License: UNKNOWN
Keywords: pprint pretty print repr sqlalchemy extension
Platform: UNKNOWN
Classifier: Development Status :: 3 - Alpha
Classifier: Operating System :: OS Independent
Classifier: Programming Language :: Python
Classifier: Programming Language :: Python :: 2
Classifier: Programming Language :: Python :: 2.6
Classifier: Programming Language :: Python :: 2.7
Classifier: Programming Language :: Python :: 3
Classifier: Programming Language :: Python :: 3.3
Classifier: Programming Language :: Python :: 3.4
Classifier: Programming Language :: Python :: 3.5
Classifier: Topic :: Database :: Front-Ends
